{"Skilldeliver": {"questions": [{"question": "В кой ред авторът на всички творби е Елин Пелин?", "choices": ["„Андрешко“, „Занемелите камбани“, „Косачи“", "„Ветрената мелница“, „Гераците“, „Ралица“", "„Задушница“, „Заточеници“, „На оня свят“", "„Мечтатели“, „Последна радост“, „Андрешко“"]}, {"question": "Автор на цикъла \"Децата на града\" е?", "choices": ["Христо Смирненски", "Пейо Яворов", "Елин Пелин", "Димчо Дебелянов"]}, {"question": "В епическата творба епизодът, в който сюжетното действие достига своята връхна точка, се нарича:", "choices": ["кулминация", "експозиция", "завръзка", "хипербола"]}], "author_img": "https://i.imgur.com/AqoLZQH.png"}}